dengraph/__about__.py
dengraph/__init__.py
dengraph/cluster.py
dengraph/compat.py
dengraph/compat3.py
dengraph/dengraph.py
dengraph/dengraphvio.py
dengraph/distance.py
dengraph/graph.py
dengraph/distances/__init__.py
dengraph/distances/delta_distance.py
dengraph/graphs/__init__.py
dengraph/graphs/adjacency_graph.py
dengraph/graphs/distance_graph.py
dengraph/graphs/graph_io.py
dengraph/primitives/__init__.py
dengraph/primitives/edge.py
dengraph/quality/__init__.py
dengraph/quality/calinski_harabasz.py
dengraph/quality/davies_bouldin.py
dengraph/quality/inter_intra.py
dengraph/quality/silhouette.py
dengraph/utilities/__init__.py
dengraph/utilities/placeholder.py
dengraph/utilities/pretty.py
dengraph-0.1.dev0.dist-info/DESCRIPTION.rst
dengraph-0.1.dev0.dist-info/METADATA
dengraph-0.1.dev0.dist-info/RECORD
dengraph-0.1.dev0.dist-info/WHEEL
dengraph-0.1.dev0.dist-info/metadata.json
dengraph-0.1.dev0.dist-info/top_level.txt
