Metadata-Version: 2.0
Name: dengraph
Version: 0.1.dev0
Summary: UNKNOWN
Home-page: UNKNOWN
Author: Eileen Kuehn, Max Fischer
Author-email: maxfischer2781@gmail.com
License: UNKNOWN
Keywords: clustering cluster graph density distance
Platform: UNKNOWN
Classifier: Development Status :: 3 - Alpha
Classifier: Intended Audience :: Information Technology
Classifier: Intended Audience :: Science/Research
Classifier: Programming Language :: Python :: 2.7
Classifier: Programming Language :: Python :: 3.3
Classifier: Programming Language :: Python :: 3.4
Classifier: Programming Language :: Python :: 3.5
Classifier: Programming Language :: Python :: Implementation :: CPython
Classifier: Programming Language :: Python :: Implementation :: PyPy
Classifier: Topic :: Scientific/Engineering :: Information Analysis
Classifier: Topic :: Software Development :: Libraries :: Python Modules
Classifier: Topic :: System :: Clustering
Requires-Dist: backports.range
